[{"model": "app_site.service", "pk": 1, "fields": {"name": "Water tap repair", "type": "PL"}}, {"model": "app_site.service", "pk": 2, "fields": {"name": "Changing the water tap", "type": "PL"}}, {"model": "app_site.service", "pk": 3, "fields": {"name": "Electrical wiring repair", "type": "EL"}}, {"model": "app_site.service", "pk": 4, "fields": {"name": "Cleaning sewer", "type": "PL"}}, {"model": "app_site.service", "pk": 5, "fields": {"name": "Window repair", "type": "OT"}}, {"model": "app_site.service", "pk": 6, "fields": {"name": "Toilet installation", "type": "PL"}}, {"model": "app_site.service", "pk": 7, "fields": {"name": "TV bracket installation", "type": "FT"}}, {"model": "app_site.service", "pk": 8, "fields": {"name": "Air conditioner installation", "type": "SP"}}, {"model": "app_site.service", "pk": 9, "fields": {"name": "Lighting installation", "type": "EL"}}, {"model": "app_site.service", "pk": 10, "fields": {"name": "Changing a sink siphon", "type": "PL"}}, {"model": "app_site.service", "pk": 11, "fields": {"name": "Door repair", "type": "OT"}}, {"model": "app_site.service", "pk": 12, "fields": {"name": "Water tap repair", "type": "PL"}}, {"model": "app_site.service", "pk": 13, "fields": {"name": "Furniture repair", "type": "FT"}}, {"model": "app_site.service", "pk": 14, "fields": {"name": "Cleaning the air conditioner", "type": "SP"}}, {"model": "app_site.service", "pk": 15, "fields": {"name": "Changing hosepipe", "type": "PL"}}, {"model": "app_site.service", "pk": 16, "fields": {"name": "Window sill installation", "type": "OT"}}, {"model": "app_site.service", "pk": 17, "fields": {"name": "Installing curtain rods", "type": "OT"}}, {"model": "app_site.service", "pk": 18, "fields": {"name": "Lamp installation", "type": "EL"}}, {"model": "app_site.service", "pk": 19, "fields": {"name": "Minor repairs", "type": null}}, {"model": "app_site.service", "pk": 20, "fields": {"name": "Water tap Instalation", "type": "PL"}}, {"model": "app_site.service", "pk": 21, "fields": {"name": "Sink installation", "type": "PL"}}, {"model": "app_site.service", "pk": 22, "fields": {"name": "Installation of shower cabin", "type": "PL"}}, {"model": "app_site.service", "pk": 23, "fields": {"name": "Installation of curtain rods", "type": "FT"}}, {"model": "app_site.service", "pk": 24, "fields": {"name": "Furniture making", "type": "FT"}}, {"model": "app_site.service", "pk": 25, "fields": {"name": "Sewer repair", "type": "PL"}}, {"model": "app_site.service", "pk": 26, "fields": {"name": "Fan installation", "type": "SP"}}, {"model": "app_site.service", "pk": 27, "fields": {"name": "Dishwasher installation", "type": "ID"}}, {"model": "app_site.service", "pk": 28, "fields": {"name": "TV installation", "type": "ID"}}, {"model": "app_site.service", "pk": 29, "fields": {"name": "Washing machine installation", "type": "ID"}}, {"model": "app_site.service", "pk": 30, "fields": {"name": "Mirror installation", "type": "ID"}}, {"model": "app_site.service", "pk": 31, "fields": {"name": "Dismantling work", "type": "BL"}}, {"model": "app_site.service", "pk": 32, "fields": {"name": "Installation works", "type": "BL"}}, {"model": "app_site.service", "pk": 33, "fields": {"name": "Repair works", "type": "PL"}}, {"model": "app_site.service", "pk": 34, "fields": {"name": "Windows clining", "type": "CL"}}, {"model": "app_site.service", "pk": 35, "fields": {"name": "Air conditioner repair", "type": "SP"}}, {"model": "app_site.service", "pk": 36, "fields": {"name": "Toilet repair", "type": "PL"}}, {"model": "app_site.service", "pk": 37, "fields": {"name": "Door installation", "type": "OT"}}, {"model": "app_site.service", "pk": 38, "fields": {"name": "Electrical panel installation", "type": "EL"}}, {"model": "app_site.service", "pk": 39, "fields": {"name": "Electrical dismantling", "type": "EL"}}, {"model": "app_site.service", "pk": 40, "fields": {"name": "Electrical wiring installation", "type": "EL"}}, {"model": "app_site.service", "pk": 41, "fields": {"name": "Installation of 220 V socket.", "type": "EL"}}, {"model": "app_site.service", "pk": 42, "fields": {"name": "Installation of 380 V socket.", "type": "EL"}}, {"model": "app_site.service", "pk": 43, "fields": {"name": "Plug in equipment", "type": "EL"}}, {"model": "app_site.service", "pk": 44, "fields": {"name": "Drywall works", "type": "BL"}}, {"model": "app_site.service", "pk": 45, "fields": {"name": "Installation of pictures/frames", "type": "ID"}}, {"model": "app_site.service", "pk": 46, "fields": {"name": "Shelf installation", "type": "FT"}}, {"model": "app_site.service", "pk": 47, "fields": {"name": "Furniture assembly", "type": "FT"}}, {"model": "app_site.service", "pk": 48, "fields": {"name": "Repair/change lock", "type": "OT"}}, {"model": "app_site.service", "pk": 49, "fields": {"name": "Diagnostics", "type": "EL"}}, {"model": "app_site.service", "pk": 50, "fields": {"name": "Putty works", "type": "BL"}}, {"model": "app_site.service", "pk": 51, "fields": {"name": "Painting the walls", "type": "BL"}}, {"model": "app_site.service", "pk": 52, "fields": {"name": "Minor repairs", "type": "BL"}}, {"model": "app_site.service", "pk": 53, "fields": {"name": "Instalation works", "type": "ID"}}, {"model": "app_site.service", "pk": 54, "fields": {"name": "Fan installation", "type": "ID"}}, {"model": "app_site.service", "pk": 55, "fields": {"name": "Sealing", "type": "PL"}}, {"model": "app_site.service", "pk": 56, "fields": {"name": "Repair work", "type": "ID"}}, {"model": "app_site.service", "pk": 57, "fields": {"name": "Water filter installation", "type": "PL"}}, {"model": "app_site.service", "pk": 58, "fields": {"name": "Installing a disposer in a sink", "type": "PL"}}, {"model": "app_site.service", "pk": 59, "fields": {"name": "Install works", "type": "PL"}}, {"model": "app_site.service", "pk": 60, "fields": {"name": "Changing a window", "type": "OT"}}, {"model": "app_site.service", "pk": 61, "fields": {"name": "Radiator Installation", "type": "PL"}}, {"model": "app_site.service", "pk": 62, "fields": {"name": "Removing a battery", "type": "PL"}}, {"model": "app_site.service", "pk": 63, "fields": {"name": "wall insulation", "type": "BL"}}, {"model": "app_site.service", "pk": 64, "fields": {"name": "diagnostics", "type": "PL"}}, {"model": "app_site.service", "pk": 65, "fields": {"name": "Wallpaper works", "type": "BL"}}, {"model": "app_site.service", "pk": 66, "fields": {"name": "Repair a cable", "type": "EL"}}, {"model": "app_site.service", "pk": 67, "fields": {"name": "Repair work", "type": "BL"}}, {"model": "app_site.service", "pk": 68, "fields": {"name": "შხაპის დალუქვა", "type": "PL"}}, {"model": "app_site.service", "pk": 69, "fields": {"name": "აღჭურვილობის შეკეთება და დიაგნოსტიკა", "type": "ID"}}]